LICENSE.txt
MANIFEST.in
README.rst
setup.py
src/django_twitterbootstrap_form.egg-info/PKG-INFO
src/django_twitterbootstrap_form.egg-info/SOURCES.txt
src/django_twitterbootstrap_form.egg-info/dependency_links.txt
src/django_twitterbootstrap_form.egg-info/namespace_packages.txt
src/django_twitterbootstrap_form.egg-info/requires.txt
src/django_twitterbootstrap_form.egg-info/top_level.txt
src/geelweb/__init__.py
src/geelweb/django/__init__.py
src/geelweb/django/twitter_bootstrap_form/__init__.py
src/geelweb/django/twitter_bootstrap_form/settings.py
src/geelweb/django/twitter_bootstrap_form/widgets.py
src/geelweb/django/twitter_bootstrap_form/templates/twitter_bootstrap_form/field.html
src/geelweb/django/twitter_bootstrap_form/templates/twitter_bootstrap_form/form.html
src/geelweb/django/twitter_bootstrap_form/templates/twitter_bootstrap_form/horizontal_field.html
src/geelweb/django/twitter_bootstrap_form/templates/twitter_bootstrap_form/inline_field.html
src/geelweb/django/twitter_bootstrap_form/templates/twitter_bootstrap_form/search_field.html
src/geelweb/django/twitter_bootstrap_form/templatetags/__init__.py
src/geelweb/django/twitter_bootstrap_form/templatetags/twitter_bootstrap.py