Metadata-Version: 1.1
Name: django-twitterbootstrap-form
Version: 0.3.2
Summary: Render Django forms as described using the twitter bootstrap HTML layout
Home-page: https://github.com/geelweb/django-twitter-bootstrap-form
Author: Guillaume Luchet
Author-email: <guillaume@geelweb.org>
License: MIT
Download-URL: https://github.com/geelweb/django-twitter-bootstrap-form/tarball/0.3.2
Keywords: django,twitter,bootstrap,form
Platform: UNKNOWN
